fastglmm/__init__.py
fastglmm/fastglmm.py
fastglmm-0.1.0.dist-info/licenses/LICENSE
fastglmm-0.1.0.dist-info/METADATA
fastglmm-0.1.0.dist-info/WHEEL
fastglmm-0.1.0.dist-info/top_level.txt
fastglmm-0.1.0.dist-info/RECORD
