Metadata-Version: 2.4
Name: fastglmm
Version: 0.1.0
Summary: Fast Generalized Linear Mixed Models in Python
Author-email: Ali Akbari <alek0991@gmail.com>
Requires-Python: >=3.8
License-File: LICENSE
Requires-Dist: pandas
Dynamic: license-file
